notebooks/Marchenko.ipynb
notebooks/Marchenko_demultiple.ipynb
notebooks/Marchenko_imaging.ipynb
notebooks/Marchenko_iterative.ipynb
notebooks/Marchenko_missing.ipynb
notebooks/Rayleigh_Marchenko.ipynb
notebooks/Rayleigh_Marchenko_dataprep.ipynb
notebooks/Rayleigh_Marchenko_imaging.ipynb
notebooks/Rayleigh_Marchenko_testdata.ipynb
notebooks/Rayleigh_Marchenko_wavsep.ipynb
notebooks/Rayleigh_Marchenko_with_pythonsep.ipynb
pymarchenko/__init__.py
pymarchenko/anglegather.py
pymarchenko/imaging.py
pymarchenko/marchenko.py
pymarchenko/mme.py
pymarchenko/neumarchenko.py
pymarchenko/raymarchenko.py
pymarchenko/version.py
pymarchenko/wavefieldsep.py
scripts/Rayleigh_Marchenko_imaging.py
scripts/Rayleigh_Marchenko_imaging.sh
scripts/rayimaging_depth_level.py
pymarchenko-0.2.0.dist-info/LICENSE
pymarchenko-0.2.0.dist-info/METADATA
pymarchenko-0.2.0.dist-info/WHEEL
pymarchenko-0.2.0.dist-info/top_level.txt
pymarchenko-0.2.0.dist-info/RECORD
