Metadata-Version: 2.1
Name: pymarchenko
Version: 0.2.0
Summary: A bag of Marchenko algorithms implemented on top of PyLops
Author-email: Matteo Ravasi <matteoravasi@gmail.com>
Keywords: geophysics,inverse problems,seismic
Classifier: Development Status :: 1 - Planning
Classifier: Intended Audience :: Science/Research
Classifier: Intended Audience :: Education
Classifier: License :: OSI Approved :: GNU Lesser General Public License v3 (LGPLv3)
Classifier: Natural Language :: English
Classifier: Operating System :: OS Independent
Classifier: Programming Language :: Python :: 3 :: Only
Classifier: Programming Language :: Python :: 3.8
Classifier: Programming Language :: Python :: 3.9
Classifier: Programming Language :: Python :: 3.10
Classifier: Topic :: Scientific/Engineering :: Mathematics
License-File: LICENSE
Requires-Dist: numpy >=1.15.0
Requires-Dist: scipy >=1.8.0
Requires-Dist: pylops >=2.0.0
